xia_browser_selenium/__init__.py
xia_browser_selenium/firefox.cp39-win_amd64.pyd
xia_browser_selenium-0.0.2.dist-info/LICENSE.txt
xia_browser_selenium-0.0.2.dist-info/METADATA
xia_browser_selenium-0.0.2.dist-info/WHEEL
xia_browser_selenium-0.0.2.dist-info/top_level.txt
xia_browser_selenium-0.0.2.dist-info/RECORD
