Metadata-Version: 2.1
Name: xia-browser-selenium
Version: 0.0.2
Summary: X-I-A
Home-page: https://develop.x-i-a.com/docs/xia-browser-selenium/0.0.2/index.html
Author: X-I-A
Author-email: admin@x-i-a.com
License: UNKNOWN
Platform: UNKNOWN
Requires-Python: >=3.9
License-File: LICENSE.txt
Requires-Dist: selenium
Requires-Dist: beautifulsoup4
Requires-Dist: google-cloud-firestore
